notionhelper/__init__.py
notionhelper/helper.py
notionhelper/ml_logger.py
notionhelper-0.4.4.dist-info/METADATA
notionhelper-0.4.4.dist-info/WHEEL
notionhelper-0.4.4.dist-info/RECORD
