Metadata-Version: 2.4
Name: notionhelper
Version: 0.4.4
Summary: NotionHelper is a Python library that simplifies interactions with the Notion API, enabling easy management of databases, pages, and files within Notion workspaces.
Author-email: Jan du Plessis <drjanduplessis@icloud.com>
Requires-Python: >=3.10
Requires-Dist: mimetype>=0.1.5
Requires-Dist: notebook>=7.4.5
Requires-Dist: notion-client>=2.4.0
Requires-Dist: pandas>=2.3.1
Requires-Dist: requests>=2.32.4
Provides-Extra: dev
Requires-Dist: black>=23.0.0; extra == 'dev'
Requires-Dist: flake8>=6.0.0; extra == 'dev'
Requires-Dist: isort>=5.12.0; extra == 'dev'
Requires-Dist: mypy>=1.0.0; extra == 'dev'
Requires-Dist: pytest-asyncio>=0.21.0; extra == 'dev'
Requires-Dist: pytest-cov>=4.0.0; extra == 'dev'
Requires-Dist: pytest-mock>=3.10.0; extra == 'dev'
Requires-Dist: pytest>=7.0.0; extra == 'dev'
Provides-Extra: test
Requires-Dist: pytest-asyncio>=0.21.0; extra == 'test'
Requires-Dist: pytest-cov>=4.0.0; extra == 'test'
Requires-Dist: pytest-mock>=3.10.0; extra == 'test'
Requires-Dist: pytest>=7.0.0; extra == 'test'
